examples/__init__.py
examples/create_dataset_and_training_job.py
examples/local_storage.py
examples/training_inference_pipeline.py
tests/integration/__init__.py
tests/integration/conftest.py
tests/integration/test_checkpoints_integration.py
tests/integration/test_datasets_integration.py
tests/integration/test_environments_integration.py
tests/integration/test_gpu_types_integration.py
tests/integration/test_jobs_integration.py
tests/integration/test_models_integration.py
tests/integration/test_volumes_integration.py
tests/integration/cloudbender/__init__.py
tests/integration/cloudbender/conftest.py
tests/integration/cloudbender/test_providers_integration.py
tests/integration/cloudbender/test_regions_integration.py
tests/integration/cloudbender/test_services_integration.py
tests/integration/projects/__init__.py
tests/integration/projects/conftest.py
tests/integration/projects/test_projects_credentials_integration.py
tests/integration/projects/test_projects_data_connectors_integration.py
tests/integration/projects/test_projects_datastores_integration.py
tests/integration/projects/test_projects_integration.py
tests/integration/projects/test_projects_members_integration.py
tests/integration/projects/test_projects_secrets_integration.py
tests/integration/projects/test_projects_services_integration.py
tests/unit/__init__.py
tests/unit/conftest.py
tests/unit/test_auth_unit.py
tests/unit/test_checkpoints_unit.py
tests/unit/test_connections_unit.py
tests/unit/test_datasets_unit.py
tests/unit/test_environments_unit.py
tests/unit/test_exceptions.py
tests/unit/test_gpu_types_unit.py
tests/unit/test_jobs_unit.py
tests/unit/test_models_unit.py
tests/unit/test_trainml_unit.py
tests/unit/test_volumes_unit.py
tests/unit/cli/__init__.py
tests/unit/cli/conftest.py
tests/unit/cli/test_cli_checkpoint_unit.py
tests/unit/cli/test_cli_datasets_unit.py
tests/unit/cli/test_cli_environment_unit.py
tests/unit/cli/test_cli_gpu_unit.py
tests/unit/cli/test_cli_job_unit.py
trainml-0.5.17.dist-info/LICENSE
trainml-0.5.17.dist-info/METADATA
trainml-0.5.17.dist-info/WHEEL
trainml-0.5.17.dist-info/entry_points.txt
trainml-0.5.17.dist-info/top_level.txt
trainml-0.5.17.dist-info/RECORD
