Metadata-Version: 2.1
Name: trainml
Version: 0.5.17
Summary: trainML client SDK and command line utilities
Home-page: https://github.com/trainML/trainml-cli
Author: trainML
Author-email: support@trainml.ai
License: MIT
Platform: UNKNOWN
Classifier: License :: OSI Approved :: MIT License
Classifier: Programming Language :: Python :: 3
Classifier: Programming Language :: Python :: 3.8
Requires-Python: >=3.8
Requires-Dist: aiodocker
Requires-Dist: aiohttp
Requires-Dist: boto3
Requires-Dist: Click (>8)
Requires-Dist: python-jose[cryptography]
Requires-Dist: requests
